pcap_parallel/__init__.py
pcap_parallel-0.1.dist-info/LICENSE
pcap_parallel-0.1.dist-info/METADATA
pcap_parallel-0.1.dist-info/WHEEL
pcap_parallel-0.1.dist-info/top_level.txt
pcap_parallel-0.1.dist-info/RECORD
