Metadata-Version: 2.1
Name: pcap-parallel
Version: 0.1
Summary: A tool for processing pcap files in parallel
Home-page: https://github.com/hardaker/pcap-parallel
Author: Wes Hardaker
Author-email: opensource@hardakers.net
Classifier: Programming Language :: Python :: 3
Classifier: Operating System :: OS Independent
Requires-Python: >=3.7
License-File: LICENSE
Requires-Dist: dpkt
